suit/__init__.py
suit/admin.py
suit/compat.py
suit/config.py
suit/models.py
suit/utils.py
suit/watch_less.py
suit/widgets.py
suit/static/admin/css/forms.css
suit/static/cms/css/pages.css
suit/static/suit/bootstrap/css/bootstrap.css
suit/static/suit/bootstrap/css/bootstrap.min.css
suit/static/suit/bootstrap/img/glyphicons-halflings-white-shadow.png
suit/static/suit/bootstrap/img/glyphicons-halflings-white.png
suit/static/suit/bootstrap/img/glyphicons-halflings.png
suit/static/suit/bootstrap/js/bootstrap.js
suit/static/suit/bootstrap/js/bootstrap.min.js
suit/static/suit/css/djangocms.css
suit/static/suit/css/filer.css
suit/static/suit/css/suit.css
suit/static/suit/img/ajax-loader.gif
suit/static/suit/img/bg_left_white.gif
suit/static/suit/img/bg_pattern.jpg
suit/static/suit/img/cc_active_nav.png
suit/static/suit/img/drag-handle.png
suit/static/suit/img/glyphicons-halflings-white-nav.png
suit/static/suit/img/glyphicons-halflings-white-shadow.png
suit/static/suit/js/djangocms.js
suit/static/suit/js/jquery-1.8.3.min.js
suit/static/suit/js/jquery-2.2.4.min.js
suit/static/suit/js/jquery.autosize-min.js
suit/static/suit/js/sortables.js
suit/static/suit/js/suit-form-confirm.js
suit/static/suit/js/suit.js
suit/static/suit/less/djangocms.less
suit/static/suit/less/filer.less
suit/static/suit/less/footer.less
suit/static/suit/less/header.less
suit/static/suit/less/left-column.less
suit/static/suit/less/mixins.less
suit/static/suit/less/print.less
suit/static/suit/less/sticky-footer.less
suit/static/suit/less/suit.less
suit/static/suit/less/variables.less
suit/static/suit/less/djangocms/list.less
suit/static/suit/less/ui/actionlist.less
suit/static/suit/less/ui/box.less
suit/static/suit/less/ui/breadcrumb.less
suit/static/suit/less/ui/calendar.less
suit/static/suit/less/ui/datepicker.less
suit/static/suit/less/ui/form.less
suit/static/suit/less/ui/left-nav.less
suit/static/suit/less/ui/list.less
suit/static/suit/less/ui/login.less
suit/static/suit/less/ui/pagination.less
django_suit_squad-0.2.29.dist-info/LICENSE
django_suit_squad-0.2.29.dist-info/METADATA
django_suit_squad-0.2.29.dist-info/WHEEL
django_suit_squad-0.2.29.dist-info/top_level.txt
django_suit_squad-0.2.29.dist-info/RECORD
